all_of_it/__init__.py
all_of_it/test.py
all_of_it-0.1.2.dist-info/WHEEL
all_of_it-0.1.2.dist-info/METADATA
all_of_it-0.1.2.dist-info/RECORD
