Metadata-Version: 2.1
Name: all-of-it
Version: 0.1.2
Summary: 
Author: Isaiah Day
Author-email: dont@stalk.me
Requires-Python: >=3.8,<4.0
Classifier: Programming Language :: Python :: 3
Classifier: Programming Language :: Python :: 3.8
Requires-Dist: requests (>=2.25.1,<3.0.0)
